{
    "environment": "local",
    "execution": {
        "cumulative_duration": 8822,
        "duration": 8857,
        "end_time": 1729089356.9360926,
        "start_time": 1729089348.0790207
    },
    "host_data": {
        "machine": "AMD64",
        "node": "HP-2",
        "pip": "24.2",
        "python": "3.12.6.final.0",
        "release": "11",
        "system": "Windows",
        "version": "10.0.22631"
    },
    "results": [
        {
            "duration": 8822,
            "id": "b79bf0ff-5482-4dcc-91b4-55a8553b6dbe",
            "status": "passed",
            "thread": "30728-MainThread",
            "title": "User should be able see all the required elements on login page"
        }
    ],
    "stats": {
        "broken": 0,
        "failed": 0,
        "muted": 0,
        "passed": 1,
        "skipped": 0,
        "total": 1
    },
    "suites": [],
    "threads": [
        "30728-MainThread"
    ],
    "title": "Test run"
}